{"name":"t:sections.header.name","type":"header","sections":{"announcement-bar":{"type":"announcement-bar","blocks":{"7387d40b-469e-4369-a613-0d11c4b82689":{"type":"block","settings":{"content":"<p><strong>ADIDAS SUPER PEGASUS - RESERVE NOW<\/strong><\/p>","link":""}},"f7579f87-bf3c-4c53-9a56-533113ce2d77":{"type":"block","settings":{"content":"<p><strong>ADIDAS SUPER PEGASUS - RESERVE NOW<\/strong><\/p>","link":""}}},"block_order":["7387d40b-469e-4369-a613-0d11c4b82689","f7579f87-bf3c-4c53-9a56-533113ce2d77"],"settings":{"enable_bar":true,"background":"#00a940","text_color":"#ffffff","show_close_option":true,"show_arrows":true,"enable_autoplay":true,"cycle_speed":5}},"header":{"type":"header","settings":{"align_logo":"inline","enable_overlap_header":true,"enable_sticky_header":false,"header_fallback_image":"shopify:\/\/shop_images\/login.png","header_fallback_image_opacity":50,"enable_header_fallback_image":true,"show_top_line_separator":true,"logo":"shopify:\/\/shop_images\/Futstrikers_LOGO_1.png","logo_max_width":95,"main_linklist":"","main_linklist_style":"uppercase","email_text":"info@futstrikers.com","phone_number":"+1 800-555-1234","show_currency_selector":true,"show_locale_selector":true,"top_navigation_linklist":"","categories_linklist":"","show_search_filter":true,"enable_live_search":true,"search_popular_searches":"","search_popular_products":""}}},"order":["announcement-bar","header"]}